constrafor_sample/__init__.py
constrafor_sample/sample.py
constrafor_sample-0.0.4.dist-info/licenses/LICENSE
constrafor_sample-0.0.4.dist-info/METADATA
constrafor_sample-0.0.4.dist-info/WHEEL
constrafor_sample-0.0.4.dist-info/top_level.txt
constrafor_sample-0.0.4.dist-info/RECORD
